{
  "name": "Cocytus",
  "creators": "CAKEC0DER & taliix",
  "official_difficulty": "3💣",
  "punter_scale_difficulty_rating": "5.69",
  "aldr_id": "125",
  "code_hash": "a31be8bb120cae7b3d99018feab36abffa6449197b9f8814a7bd08b05429f185",
  "source": "https://scratch.mit.edu/projects/1037279101",
  "other_difficulty_system_ratings": {
    "skills_balance": "0.5",
    "ahll_rank": "102"
  },
  "michael_chan_extended_difficulty_rating": "1💣",
  "ahll_difficulty": "Mid 1💣",
  "ahll_id": "424",
  "notes": "Verifier/First Victor: Krackerz\nFastest Time: cwktao - 15.70"
}
